apix/__init__.py
apix/diff.py
apix/explore.py
apix/helpers.py
apix/parsers/__init__.py
apix/parsers/apipie.py
apix/parsers/test.py
candore/__init__.py
candore/cli.py
candore/config.py
candore/errors.py
candore/utils.py
candore/modules/__init__.py
candore/modules/api_lister.py
candore/modules/comparator.py
candore/modules/extractor.py
candore/modules/finder.py
candore/modules/report.py
candore/modules/ssh.py
candore/modules/variations.py
candore/modules/webapp.py
candore/modules/templates/table.html
candore-1.4.0.dist-info/METADATA
candore-1.4.0.dist-info/WHEEL
candore-1.4.0.dist-info/entry_points.txt
candore-1.4.0.dist-info/licenses/LICENSE
candore-1.4.0.dist-info/RECORD
