Metadata-Version: 2.3
Name: candore
Version: 1.4.0
Author: Jitendra Yejare
Maintainer: Jitendra Yejare
License-File: LICENSE
Keywords: api,data,distutils,hatch,upgrades,validation
Requires-Dist: aiohttp
Requires-Dist: asyncio
Requires-Dist: click
Requires-Dist: dynaconf
Requires-Dist: flask
Requires-Dist: hussh
Requires-Dist: logzero
Requires-Dist: lxml
Requires-Dist: pyyaml
Requires-Dist: requests
Provides-Extra: test
Requires-Dist: coveralls; extra == 'test'
Requires-Dist: mock; extra == 'test'
Requires-Dist: pre-commit; extra == 'test'
Requires-Dist: pytest; extra == 'test'
Requires-Dist: pytest-cov; extra == 'test'
Requires-Dist: pytest-mock; extra == 'test'
Requires-Dist: pytest-variables; extra == 'test'
